README.md
setup.cfg
setup.py
argparsex/__init__.py
argparsex.egg-info/PKG-INFO
argparsex.egg-info/SOURCES.txt
argparsex.egg-info/dependency_links.txt
argparsex.egg-info/top_level.txt